kdpeak/__init__.py
kdpeak/core.py
kdpeak/util.py
kdpeak-0.2.0.dist-info/LICENSE
kdpeak-0.2.0.dist-info/METADATA
kdpeak-0.2.0.dist-info/WHEEL
kdpeak-0.2.0.dist-info/entry_points.txt
kdpeak-0.2.0.dist-info/top_level.txt
kdpeak-0.2.0.dist-info/RECORD
