Metadata-Version: 2.1
Name: kdpeak
Version: 0.2.0
Summary: A tool to identify genomic peaks based on kernel density estimation.
Home-page: https://github.com/settylab/kdpeak
Author: Dominik Otto
Author-email: dotto@fredhutch.org
Classifier: Development Status :: 3 - Alpha
Classifier: Intended Audience :: Science/Research
Classifier: License :: OSI Approved :: GNU General Public License v3 (GPLv3)
Classifier: Natural Language :: English
Classifier: Programming Language :: Python :: 3
Classifier: Topic :: Scientific/Engineering :: Bio-Informatics
Requires-Python: >=3.7
License-File: LICENSE
Requires-Dist: numpy (>=1.20.0)
Requires-Dist: pandas (>=1.3.0)
Requires-Dist: KDEpy (>=1.0.6)
